{
  "entities": [
    {
      "name": "harry",
      "entity_type": "person",
      "singular": true,
      "description": "Harry is described as looking toward the front of the bus and seeing Hermione cover her eyes with her hands."
    },
    {
      "name": "hermione",
      "entity_type": "person",
      "singular": true,
      "description": "Hermione is described as covering her eyes with her hands on the bus."
    },
    {
      "name": "pigwidgeon",
      "entity_type": "animal",
      "singular": true,
      "description": "Pigwidgeon is described as swaying happily on Hermione's shoulder."
    },
    {
      "name": "knight bus",
      "entity_type": "vehicle",
      "singular": true,
      "description": "The Knight Bus is described as jumping from the Birmingham motorway to a quiet country lane and moving through various locations."
    },
    {
      "name": "stan",
      "entity_type": "person",
      "singular": true,
      "description": "Stan is described as swaying towards Harry and Ron on the bus."
    },
    {
      "name": "ron",
      "entity_type": "person",
      "singular": true,
      "description": "Ron is described as picking himself up from the floor for the sixth time due to the bus's movements."
    }
  ],
  "relationships": [
    {
      "entity_1": "harry",
      "entity_2": "hermione",
      "relationship_type": "saw",
      "description": "Harry saw Hermione cover her eyes with her hands on the bus."
    },
    {
      "entity_1": "knight bus",
      "entity_2": "birmingham motorway",
      "relationship_type": "moved_from",
      "description": "The Knight Bus jumped from the Birmingham motorway to a quiet country lane."
    },
    {
      "entity_1": "stan",
      "entity_2": "harry",
      "relationship_type": "swayed_towards",
      "description": "Stan swayed towards Harry on the bus."
    },
    {
      "entity_1": "ron",
      "entity_2": "knight bus",
      "relationship_type": "experienced_motion",
      "description": "Ron experienced motion sickness due to the bus's movements."
    },
    {
      "entity_1": "stan",
      "entity_2": "harry and ron",
      "relationship_type": "informed",
      "description": "Stan informed Harry and Ron that they were approaching Hogwarts stop."
    }
  ]
}