{
  "entities": [
    {
      "name": "sirius black",
      "entity_type": "person",
      "singular": true,
      "description": "believe to be Sirius Black is actually Stubby Board-man, lead singer of the popular singing group The Hobgoblins"
    },
    {
      "name": "stubby boardman",
      "entity_type": "person",
      "singular": true,
      "description": "lead singer of the popular singing group The Hobgoblins"
    },
    {
      "name": "the hobgoblins",
      "entity_type": "group",
      "singular": false,
      "description": "popular singing group"
    },
    {
      "name": "cornelius fudge",
      "entity_type": "person",
      "singular": true,
      "description": "Minister of Magic"
    }
  ],
  "relationships": [
    {
      "entity_1": "sirius black",
      "entity_2": "stubby boardman",
      "relationship_type": "is actually",
      "description": "believe to be Sirius Black is actually Stubby Board-man"
    },
    {
      "entity_1": "sirius black",
      "entity_2": "cornelius fudge",
      "relationship_type": "has been accused of crimes by",
      "description": "Now, Stubby couldn’t possibly have committed those crimes, because on the day in question he happened to be enjoying a romantic candlelit dinner with me"
    },
    {
      "entity_1": "stubby boardman",
      "entity_2": "cornelius fudge",
      "relationship_type": "has been accused of crimes by",
      "description": "Now, Stubby couldn’t possibly have committed those crimes, because on the day in question he happened to be enjoying a romantic candlelit dinner with me"
    },
    {
      "entity_1": "sirius black",
      "entity_2": "cornelius fudge",
      "relationship_type": "will receive pardon from",
      "description": "I have written to the Minister of Magic and am expecting him to give Stubby, alias Sirius, a full pardon any day now"
    },
    {
      "entity_1": "stubby boardman",
      "entity_2": "cornelius fudge",
      "relationship_type": "will receive pardon from",
      "description": "I have written to the Minister of Magic and am expecting him to give Stubby, alias Sirius, a full pardon any day now"
    }
  ]
}