{
  "entities": [
    {
      "name": "bell jar",
      "entity_type": "object",
      "singular": true,
      "description": "The bell jar is described as a container that holds the man's head and glittering wind. It is also mentioned that his head sank through the surface of the bell jar."
    },
    {
      "name": "soap bubble",
      "entity_type": "object",
      "singular": true,
      "description": "The bell jar is compared to a soap bubble, indicating its fragile and ephemeral nature."
    },
    {
      "name": "glittering wind",
      "entity_type": "object",
      "singular": false,
      "description": "The glittering wind is described as being inside the bell jar, but it is not clear what it is or where it comes from."
    },
    {
      "name": "Harry's wand",
      "entity_type": "object",
      "singular": true,
      "description": "Harry's wand is mentioned as flying into Hermione's hand and then being thrown to Harry."
    },
    {
      "name": "Hermione",
      "entity_type": "person",
      "singular": true,
      "description": "Hermione is described as throwing Harry's wand to him after it flew into her hand."
    },
    {
      "name": "Neville",
      "entity_type": "person",
      "singular": true,
      "description": "Neville is mentioned as being horrified and staring at the Death Eater's head in the bell jar."
    },
    {
      "name": "Death Eater",
      "entity_type": "person",
      "singular": true,
      "description": "The Death Eater's head is described as shrinking and changing into a baby's head."
    }
  ],
  "relationships": [
    {
      "entity_1": "bell jar",
      "entity_2": "man's head",
      "relationship_type": "contains",
      "description": "The bell jar contains the man's head, which sinks through its surface."
    },
    {
      "entity_1": "Harry",
      "entity_2": "wand",
      "relationship_type": "owns",
      "description": "Harry owns a wand that flies into Hermione's hand and then is thrown to him."
    },
    {
      "entity_1": "Hermione",
      "entity_2": "wand",
      "relationship_type": "temporarily possesses",
      "description": "Hermione temporarily possesses Harry's wand after it flew into her hand."
    },
    {
      "entity_1": "Neville",
      "entity_2": "Death Eater's head",
      "relationship_type": "observes",
      "description": "Neville observes the Death Eater's head in the bell jar and is horrified."
    }
  ]
}