{
  "entities": [
    {
      "name": "barnabas",
      "entity_type": "character",
      "singular": true,
      "description": "Barnabas is mentioned as 'the Barmy' indicating he has a nickname or a peculiar personality."
    },
    {
      "name": "trolls",
      "entity_type": "creature",
      "singular": false,
      "description": "Trolls are being trained for ballet by Barnabas."
    },
    {
      "name": "harry",
      "entity_type": "character",
      "singular": true,
      "description": "Harry is the one trying to train trolls for ballet and is described as quietly speaking."
    },
    {
      "name": "dobby",
      "entity_type": "character",
      "singular": true,
      "description": "Dobby is mentioned as giving advice on how to proceed with training trolls."
    },
    {
      "name": "ron",
      "entity_type": "character",
      "singular": true,
      "description": "Ron is part of the group trying to train trolls for ballet and is described as screwing up his eyes in concentration."
    },
    {
      "name": "hermione",
      "entity_type": "character",
      "singular": true,
      "description": "Hermione is part of the group trying to train trolls for ballet and is described as whispering something under her breath."
    }
  ],
  "relationships": [
    {
      "entity_1": "harry",
      "entity_2": "trolls",
      "relationship_type": "tries_to_train",
      "description": "Harry is trying to train trolls for ballet."
    },
    {
      "entity_1": "ron",
      "entity_2": "wall",
      "relationship_type": "walks_past",
      "description": "Ron walks past the wall with Harry and Hermione."
    }
  ]
}