{
  "entities": [
    {
      "name": "she",
      "entity_type": "person",
      "singular": true,
      "description": "refers to an unspecified female character"
    },
    {
      "name": "old Kreacher",
      "entity_type": "house-elf",
      "singular": true,
      "description": "a house-elf who is old and possibly wise"
    },
    {
      "name": "Mudbloods",
      "entity_type": "people",
      "singular": false,
      "description": "refers to people of non-magical blood"
    }
  ],
  "relationships": [
    {
      "entity_1": "she",
      "entity_2": "old Kreacher",
      "relationship_type": "addressed",
      "description": "the female character is speaking to old Kreacher"
    },
    {
      "entity_1": "she",
      "entity_2": "Mudbloods",
      "relationship_type": "referenced",
      "description": "the female character mentions Mudbloods in her conversation with old Kreacher"
    }
  ]
}