{
  "entities": [
    {
      "name": "ron",
      "entity_type": "person",
      "singular": true,
      "description": "Ron is mentioned as taking a bow and holding Harry up after he fainted."
    },
    {
      "name": "seamus",
      "entity_type": "person",
      "singular": true,
      "description": "Seamus is mentioned as asking Ron what he was after."
    },
    {
      "name": "harry",
      "entity_type": "person",
      "singular": true,
      "description": "Harry is the main character and is experiencing a terrible pain in his lightning scar."
    },
    {
      "name": "neville",
      "entity_type": "person",
      "singular": true,
      "description": "Neville is mentioned as asking Harry if he's all right and offering him a seat."
    },
    {
      "name": "hermione",
      "entity_type": "person",
      "singular": true,
      "description": "Hermione is mentioned alongside Ron in the scene where they're trying to help Harry."
    },
    {
      "name": "voldemort",
      "entity_type": "person",
      "singular": true,
      "description": "Voldemort's scream of fury is heard by Harry and he discovers that Voldemort has just discovered the loss of one of his Horcruxes."
    },
    {
      "name": "room of requirement",
      "entity_type": "location",
      "singular": true,
      "description": "The Room of Requirement is where Harry stands after being pulled out of Voldemort's mind."
    }
  ],
  "relationships": [
    {
      "entity_1": "harry",
      "entity_2": "voldemort",
      "relationship_type": "has_discovered_loss_of_horcrux",
      "description": "Harry feels Voldemort's scream of fury and realizes that Voldemort has just discovered the loss of one of his Horcruxes."
    },
    {
      "entity_1": "ron",
      "entity_2": "harry",
      "relationship_type": "is_holding_up",
      "description": "Ron is holding Harry up after he fainted."
    },
    {
      "entity_1": "neville",
      "entity_2": "harry",
      "relationship_type": "is_concerned_about",
      "description": "Neville is concerned about Harry's well-being and offers him a seat."
    }
  ]
}