{
  "entities": [
    {
      "name": "caterwauling charm",
      "entity_type": "spell",
      "singular": true,
      "description": "A type of spell mentioned in the text."
    },
    {
      "name": "hogsmeade",
      "entity_type": "location",
      "singular": true,
      "description": "A village near Hogwarts where students often go on weekends."
    },
    {
      "name": "hogwarts",
      "entity_type": "school",
      "singular": true,
      "description": "The school that Harry and his friends attend."
    },
    {
      "name": "hagrid",
      "entity_type": "person",
      "singular": true,
      "description": "A gamekeeper at Hogwarts who is also a half-giant."
    },
    {
      "name": "grawp",
      "entity_type": "person",
      "singular": true,
      "description": "Hagrid's half-brother."
    },
    {
      "name": "aberforth",
      "entity_type": "person",
      "singular": true,
      "description": "Harry's uncle and a member of the Order of the Phoenix."
    },
    {
      "name": "cloak",
      "entity_type": "object",
      "singular": true,
      "description": "A magical cloak that allows the wearer to Disapparate."
    },
    {
      "name": "bowtruckles",
      "entity_type": "creature",
      "singular": false,
      "description": "Small, insect-like creatures that live on trees in the Hogwarts grounds."
    },
    {
      "name": "doxy eggs",
      "entity_type": "object",
      "singular": false,
      "description": "Eggs of a type of magical creature."
    }
  ],
  "relationships": [
    {
      "entity_1": "harry",
      "entity_2": "hogwarts",
      "relationship_type": "goal",
      "description": "Harry wants to get into Hogwarts."
    },
    {
      "entity_1": "aberforth",
      "entity_2": "harry",
      "relationship_type": "advice",
      "description": "Aberforth is advising Harry not to leave Hogsmeade."
    }
  ]
}