{
  "entities": [
    {
      "name": "hogsmeade",
      "entity_type": "location",
      "singular": true,
      "description": "Hogsmeade is a village in the Harry Potter series, mentioned as being located north of Hogwarts."
    },
    {
      "name": "gregorovitch",
      "entity_type": "person",
      "singular": true,
      "description": "Gregorovitch is a wandmaker who is rumored to have created a duplicate of the Elder Wand. He started this rumor himself for business purposes."
    },
    {
      "name": "elder wand",
      "entity_type": "object",
      "singular": true,
      "description": "The Elder Wand, also known as the Deathstick, is one of the three Deathly Hallows and a powerful magical object."
    },
    {
      "name": "deathly hallows",
      "entity_type": "concept",
      "singular": true,
      "description": "The Deathly Hallows are three powerful magical objects created by Death herself: the Elder Wand, the Resurrection Stone, and the Cloak of Invisibility."
    },
    {
      "name": "ollivander",
      "entity_type": "person",
      "singular": true,
      "description": "Ollivander is a wandmaker who is an expert in wands and their history. He denies knowing about the Deathly Hallows."
    }
  ],
  "relationships": [
    {
      "entity_1": "gregorovitch",
      "entity_2": "elder wand",
      "relationship_type": "created_duplicate_of",
      "description": "Gregorovitch created a duplicate of the Elder Wand, which he used to start a rumor about his business."
    },
    {
      "entity_1": "harry",
      "entity_2": "ollivander",
      "relationship_type": "questioned",
      "description": "Harry questioned Ollivander about the Deathly Hallows and Gregorovitch's involvement with them."
    }
  ]
}