{
  "entities": [
    {
      "name": "ron",
      "entity_type": "person",
      "singular": true,
      "description": "Ron is introduced as a character who pulls out his wand. He is also mentioned to be in Professor Flitwick's class."
    },
    {
      "name": "harry",
      "entity_type": "person",
      "singular": true,
      "description": "Harry is introduced as a character who pulls Ron away and notices something odd about Riddle's diary."
    },
    {
      "name": "riddle",
      "entity_type": "person",
      "singular": true,
      "description": "Riddle is mentioned as the owner of a diary that Harry notices something odd about."
    },
    {
      "name": "flitwick",
      "entity_type": "professor",
      "singular": true,
      "description": "Professor Flitwick is introduced as the teacher of Charms class where Ron and Harry are present."
    }
  ],
  "relationships": [
    {
      "entity_1": "harry",
      "entity_2": "ron",
      "relationship_type": "pulled_away_by",
      "description": "Harry pulled Ron away from doing something."
    },
    {
      "entity_1": "harry",
      "entity_2": "riddle's diary",
      "relationship_type": "noticed_something_odd_about",
      "description": "Harry noticed something odd about Riddle's diary."
    }
  ]
}