{
  "entities": [
    {
      "name": "Harry Potter",
      "entity_type": "person",
      "singular": true,
      "description": "The main character of the story"
    },
    {
      "name": "Ron Weasley",
      "entity_type": "person",
      "singular": true,
      "description": "Harry's best friend"
    }
  ],
  "relationships": [
    {
      "entity_1": "Harry Potter",
      "entity_2": "Ron Weasley",
      "relationship_type": "friendship",
      "description": "Their friendship is a central theme in the story"
    }
  ]
}