{
  "entities": [
    {
      "name": "hermione",
      "entity_type": "person",
      "singular": true,
      "description": "Hermione sat down on an upturned bucket, looking desperately anxious"
    },
    {
      "name": "harry",
      "entity_type": "person",
      "singular": true,
      "description": "Harry wanted a few questions answered"
    },
    {
      "name": "professor mcgonagall",
      "entity_type": "person",
      "singular": true,
      "description": "Professor McGonagall made me swear I wouldn’t tell anyone"
    },
    {
      "name": "sirius",
      "entity_type": "person",
      "singular": true,
      "description": "Why did he tell us to go back three hours? How’s that going to help Sirius?"
    }
  ],
  "relationships": [
    {
      "entity_1": "harry",
      "entity_2": "hermione",
      "relationship_type": "questioning",
      "description": "Harry wanted a few questions answered"
    },
    {
      "entity_1": "harry",
      "entity_2": "professor mcgonagall",
      "relationship_type": "inquiry",
      "description": "Why did he tell us to go back three hours? How’s that going to help Sirius?"
    },
    {
      "entity_1": "hermione",
      "entity_2": "time-turner",
      "relationship_type": "possession",
      "description": "Hermione whispered, “and I got it from Professor McGonagall on our ﬁrst day back."
    },
    {
      "entity_1": "professor mcgonagall",
      "entity_2": "hermione",
      "relationship_type": "giver",
      "description": "Professor McGonagall made me swear I wouldn’t tell anyone"
    },
    {
      "entity_1": "harry",
      "entity_2": "sirius",
      "relationship_type": "concern",
      "description": "Why did he tell us to go back three hours? How’s that going to help Sirius?"
    }
  ]
}