{
  "entities": [
    {
      "name": "grim",
      "entity_type": "noun",
      "singular": true,
      "description": "The Grim is a mysterious entity that has appeared twice, causing near-fatal accidents. It is mentioned as something Harry hasn't told anyone about."
    },
    {
      "name": "ron",
      "entity_type": "proper_noun",
      "singular": true,
      "description": "Ron is Harry's friend who would panic if he knew about the Grim."
    }
  ],
  "relationships": [
    {
      "entity_1": "grim",
      "entity_2": "ron",
      "relationship_type": "causes_panic",
      "description": "The appearance of the Grim causes Ron to panic. This relationship is described as Harry knowing that Ron would panic if he knew about the Grim."
    }
  ]
}